{"is_source_file": false, "format": "", "description": "", "external_files": [], "external_methods": [], "published": [], "classes": [], "methods": [], "calls": [], "search-terms": [], "state": 2, "file_id": 5, "knowledge_revision": 18, "git_revision": "75dcd22c5f7fca8d5eba34ae2998b54198dfe196", "ctags": [], "hash": "1a77571e1a8cf36018a41bcedf60db75", "format-version": 4, "code-base-name": "notes_frontend", "filename": "notes_frontend/src/setupTests.js", "revision_history": [{"18": "75dcd22c5f7fca8d5eba34ae2998b54198dfe196"}]}